aics_tf_registration/__init__.py
aics_tf_registration/bin/__init__.py
aics_tf_registration/bin/run_alignment.py
aics_tf_registration/core/__init__.py
aics_tf_registration/core/alignment.py
aics_tf_registration/core/image_aligner.py
aics_tf_registration/core/preprocessing.py
aics_tf_registration-0.1.1.dist-info/LICENSE
aics_tf_registration-0.1.1.dist-info/METADATA
aics_tf_registration-0.1.1.dist-info/WHEEL
aics_tf_registration-0.1.1.dist-info/entry_points.txt
aics_tf_registration-0.1.1.dist-info/top_level.txt
aics_tf_registration-0.1.1.dist-info/RECORD
